pi_common_sensors/GPIO_engine.py
pi_common_sensors/__init__.py
pi_common_sensors/controls.py
pi_common_sensors/data.py
pi_common_sensors/monitors.py
pi_common_sensors/rpi_usb.py
pi_common_sensors/gravity/DFRobot_BME280.py
pi_common_sensors/gravity/DFRobot_BME680.py
pi_common_sensors/gravity/__init__.py
pi_common_sensors-0.3.0.dist-info/LICENSE
pi_common_sensors-0.3.0.dist-info/METADATA
pi_common_sensors-0.3.0.dist-info/WHEEL
pi_common_sensors-0.3.0.dist-info/top_level.txt
pi_common_sensors-0.3.0.dist-info/RECORD
