Metadata-Version: 2.1
Name: pi_common_sensors
Version: 0.3.0
Summary: This package provides additional suite of python based rpi abstraction for handling rpi hardware control.
Home-page: https://github.com/mohas95/pi_common_sensors
Author: Mohamed Debbagh
Author-email: moha.debbagh95@gmail.com
License: GNU GPLv3
Project-URL: Bug Tracker, https://github.com/mohas95/pi_common_sensors/issues
Project-URL: Github, https://github.com/mohas95/pi_common_sensors
Keywords: Raspberry Pi,Raspi,Python,GPIO,USB,Mass storage,API,non-blocking
Classifier: Programming Language :: Python :: 3
Classifier: License :: OSI Approved :: GNU General Public License v3 (GPLv3)
Classifier: Operating System :: POSIX :: Linux
Classifier: Development Status :: 3 - Alpha
Requires-Python: >=3.6
License-File: LICENSE
Requires-Dist: logzero
Requires-Dist: RPi.GPIO
Requires-Dist: pigpio
Requires-Dist: smbus
Requires-Dist: spidev
Requires-Dist: pyserial
